acore/__init__.py
acore/utils.py
acore/wgcna_analysis.py
acore/correlation_analysis/__init__.py
acore/decomposition/__init__.py
acore/decomposition/pca.py
acore/decomposition/umap.py
acore/differential_regulation/__init__.py
acore/differential_regulation/format_test_table.py
acore/differential_regulation/tests.py
acore/enrichment_analysis/__init__.py
acore/enrichment_analysis/annotate.py
acore/enrichment_analysis/statistical_tests/fisher.py
acore/enrichment_analysis/statistical_tests/kolmogorov_smirnov.py
acore/exploratory_analysis/__init__.py
acore/imputation_analysis/__init__.py
acore/io/__init__.py
acore/io/ftp.py
acore/io/http.py
acore/io/pride.py
acore/io/uncompress.py
acore/io/uniprot/__init__.py
acore/io/uniprot/uniprot.py
acore/kaplan_meier_analysis/__init__.py
acore/multiple_testing/__init__.py
acore/network_analysis/__init__.py
acore/normalization/__init__.py
acore/normalization/strategies.py
acore/power_analysis/__init__.py
acore/publications_analysis/__init__.py
acore/sklearn/__init__.py
acore/tda_analysis/__init__.py
acore-0.2.0.dist-info/licenses/AUTHORS.rst
acore-0.2.0.dist-info/licenses/LICENSE
acore-0.2.0.dist-info/METADATA
acore-0.2.0.dist-info/WHEEL
acore-0.2.0.dist-info/top_level.txt
acore-0.2.0.dist-info/RECORD
